{
	"class" : {
		"taskbarIcon" : "gvc 5/21/2007 12:41" },
	"instance" : {
		"actionSelector" : "gvc 8/27/2006 10:33",
		"actionSelector:" : "gvc 8/27/2006 10:33",
		"addInitialPanel" : "gvc 8/24/2006 10:49",
		"answer" : "gvc 8/31/2006 15:19",
		"answer:" : "gvc 7/30/2009 14:00",
		"answerDirectory" : "gvc 3/23/2007 16:04",
		"answerFileEntry" : "gvc 4/4/2007 16:08",
		"answerFileName" : "gvc 4/4/2007 16:00",
		"answerForceSaveFile" : "gvc 3/23/2007 16:04",
		"answerOpenFile" : "gvc 3/23/2007 16:04",
		"answerPathName" : "gvc 3/23/2007 16:04",
		"answerSaveFile" : "gvc 3/23/2007 16:04",
		"cache:" : "gvc 9/27/2006 11:38",
		"clearEntryCache" : "gvc 4/24/2007 11:23",
		"defaultExtension" : "gvc 10/11/2006 13:33",
		"defaultExtension:" : "gvc 10/11/2006 13:33",
		"defaultFileSelectionBlock" : "stephane.ducasse 4/13/2009 21:06",
		"defaultFileSortBlock" : "stephane.ducasse 4/13/2009 21:06",
		"defaultLabel" : "gvc 8/23/2006 14:19",
		"deleteFileOrDirectory" : "gvc 4/24/2007 11:29",
		"directories" : "gvc 8/23/2006 14:19",
		"directories:" : "gvc 8/23/2006 14:19",
		"directoryFileSelectionBlock" : "stephane.ducasse 4/13/2009 21:06",
		"directoryNamesFor:" : "gvc 8/23/2006 14:29",
		"directoryTreeMorph" : "gvc 8/23/2006 19:51",
		"directoryTreeMorph:" : "gvc 8/23/2006 19:51",
		"doubleClickFile" : "gvc 1/15/2007 15:13",
		"entryCache" : "gvc 9/27/2006 10:21",
		"entryCache:" : "gvc 9/27/2006 10:21",
		"entryCacheDirectory" : "gvc 9/27/2006 10:21",
		"entryCacheDirectory:" : "gvc 9/27/2006 10:21",
		"fileItems" : "gvc 4/16/2007 11:07",
		"fileListMorph" : "gvc 8/23/2006 19:51",
		"fileListMorph:" : "gvc 8/23/2006 19:51",
		"fileNamePattern" : "gvc 8/24/2006 16:13",
		"fileNameText" : "gvc 8/24/2006 15:54",
		"fileNameText:" : "gvc 4/3/2007 15:19",
		"fileSelectionBlock" : "gvc 8/24/2006 08:39",
		"fileSelectionBlock:" : "gvc 8/24/2006 08:45",
		"fileSortBlock" : "gvc 8/24/2006 08:51",
		"fileSortBlock:" : "gvc 8/24/2006 08:51",
		"files" : "gvc 9/27/2006 11:39",
		"hasParentDirectory" : "gvc 4/24/2007 10:21",
		"hasSelectedFileOrDirectory" : "gvc 4/24/2007 10:17",
		"iconFor:" : "gvc 9/27/2006 13:50",
		"initialDirectories" : "gvc 8/23/2006 14:18",
		"initialize" : "gvc 7/30/2009 14:01",
		"isImageFile:" : "gvc 10/9/2006 13:53",
		"isResizeable" : "gvc 9/22/2009 11:17",
		"newActionButtonRow" : "gvc 4/24/2007 10:39",
		"newContentMorph" : "gvc 9/22/2009 10:55",
		"newDeleteButton" : "gvc 4/21/2009 17:00",
		"newDirectory" : "gvc 4/24/2007 11:19",
		"newDirectoryTree" : "gvc 9/22/2009 10:54",
		"newFileList" : "gvc 8/9/2007 13:29",
		"newFileNameTextEntry" : "gvc 4/3/2007 15:20",
		"newImagePreviewMorph" : "gvc 5/14/2007 16:33",
		"newNewDirectoryButton" : "gvc 4/21/2009 17:01",
		"newOKButton" : "gvc 3/23/2007 15:59",
		"newPreviewMorph" : "gvc 5/14/2007 16:24",
		"newTextPreviewMorph" : "gvc 5/14/2007 16:39",
		"newUpButton" : "gvc 4/21/2009 17:01",
		"ok" : "gvc 1/10/2007 10:41",
		"okEnabled" : "gvc 4/4/2007 16:34",
		"openSelectedFile" : "gvc 3/23/2007 15:51",
		"previewMorph" : "gvc 9/27/2006 13:55",
		"previewMorph:" : "gvc 9/27/2006 13:55",
		"previewSize" : "gvc 5/14/2007 16:38",
		"previewType" : "gvc 9/27/2006 13:30",
		"previewType:" : "gvc 5/14/2007 16:42",
		"saveForcedSelectedFile" : "gvc 1/15/2007 15:13",
		"saveSelectedFile" : "gvc 5/1/2007 12:22",
		"selectDirectory:" : "gvc 8/24/2006 10:49",
		"selectFileFromPattern" : "gvc 5/2/2007 12:19",
		"selectParentDirectory" : "gvc 4/24/2007 10:43",
		"selectPathName:" : "gvc 1/15/2007 15:04",
		"selectedAnyFileDirectory" : "gvc 1/15/2007 15:21",
		"selectedDirectory" : "gvc 8/23/2006 14:33",
		"selectedDirectory:" : "gvc 8/24/2006 08:49",
		"selectedDirectoryName" : "gvc 1/15/2007 15:14",
		"selectedFileDirectory" : "gvc 1/15/2007 15:13",
		"selectedFileEntry" : "gvc 11/5/2008 12:09",
		"selectedFileIndex" : "gvc 8/23/2006 15:42",
		"selectedFileIndex:" : "gvc 8/24/2006 08:46",
		"selectedFileName" : "gvc 8/23/2006 17:02",
		"selectedPathName" : "gvc 1/15/2007 15:14",
		"showDirectoriesInFileList" : "gvc 8/24/2006 08:42",
		"showDirectoriesInFileList:" : "gvc 8/24/2006 08:44",
		"updateDirectories" : "gvc 7/30/2009 14:01",
		"updateFiles" : "gvc 8/24/2006 08:46",
		"updateImagePreview" : "gvc 5/14/2007 16:33",
		"updatePreview" : "gvc 5/14/2007 16:25",
		"updateSelectedDirectory" : "gvc 4/24/2007 10:41",
		"updateSelectedFile" : "gvc 4/24/2007 10:40",
		"updateTextPreview" : "gvc 5/14/2007 16:36",
		"validExtensions:" : "stephane.ducasse 4/13/2009 21:06" } }
