{
	"class" : {
		"loadSqueakMap" : "ar 9/27/2005 20:13",
		"registerOpenCommand:" : "sw 11/10/2002 22:56",
		"registeredOpenCommands" : "nk 6/29/2003 13:56",
		"registry" : "nk 6/29/2003 13:55",
		"removeObsolete" : "ar 9/27/2005 21:49",
		"unregisterOpenCommand:" : "nk 6/29/2003 13:55",
		"unregisterOpenCommandWithReceiver:" : "nk 6/29/2003 13:55" },
	"instance" : {
		"adaptToWorld:" : "adrian_lienhard 7/21/2009 19:12",
		"appearanceDo" : "RAA 5/26/2000 10:25",
		"appearanceMenu" : "MiguelCoba 7/25/2009 02:21",
		"buildWorldMenu" : "damiencassou 7/31/2009 12:10",
		"changeBackgroundColor" : "ar 10/5/2000 18:54",
		"changesMenu" : "al 10/23/2008 20:43",
		"cleanUpWorld" : "alain.plantec 2/6/2009 17:36",
		"commandKeyMappings" : "TestRunner 10/30/2009 00:01",
		"commandKeyTypedIntoMenu:" : "sw 12/4/2001 21:02",
		"debugMenu" : "stephane.ducasse 7/20/2009 19:37",
		"doMenuItem:with:" : "marcus.denker 6/10/2009 20:21",
		"doPopUp:" : "RAA 6/12/2000 09:13",
		"fillIn:from:" : "sd 3/1/2008 21:14",
		"garbageCollect" : "nk 2/15/2004 09:37",
		"helpMenu" : "marcus.denker 9/19/2008 18:33",
		"lookForSlips" : "sd 5/23/2003 14:49",
		"menu:" : "marcus.denker 9/19/2008 16:54",
		"menuColorString" : "RAA 5/26/2000 10:18",
		"openBrowser" : "ar 9/27/2005 20:33",
		"openCommandKeyHelp" : "stephane.ducasse 7/10/2009 15:54",
		"openFileList" : "hfm 11/29/2008 20:06",
		"openMenu" : "al 10/23/2008 20:40",
		"openTranscript" : "RAA 5/24/2000 18:53",
		"openWorkspace" : "ar 9/27/2005 20:49",
		"quitSession" : "lr 7/5/2009 23:37",
		"registeredToolsDo" : "al 10/12/2008 21:25",
		"registeredToolsMenu" : "al 10/12/2008 21:26",
		"roundedCornersString" : "RAA 5/26/2000 10:18",
		"saveAndQuit" : "lr 7/4/2009 19:30",
		"saveAs" : "lr 7/4/2009 19:28",
		"saveWorldInFile" : "DamienCassou 9/23/2009 08:53",
		"setDisplayDepth" : "alain.plantec 2/6/2009 17:38",
		"setGradientColor" : "RAA 6/27/2000 09:04",
		"soundEnablingString" : "RAA 5/26/2000 08:35",
		"standardFontDo" : "RAA 5/26/2000 10:27",
		"startMessageTally" : "stephane.ducasse 7/20/2009 19:34",
		"startThenBrowseMessageTally" : "stephane.ducasse 7/20/2009 19:35",
		"suppressFlapsString" : "dao 10/1/2004 13:12",
		"systemMenu" : "marcus.denker 8/1/2009 13:28",
		"toggleScreenString" : "RobRothwell 2/23/2009 22:42",
		"vmStatistics" : "nk 2/15/2004 09:31",
		"windowsMenu" : "al 10/23/2008 20:40",
		"world:project:hand:" : "RAA 5/24/2000 19:02" } }
