{
	"class" : {
		"defaultNameStemForInstances" : "dgd 8/26/2004 12:11",
		"initialize" : "GabrielOmarCotelli 6/4/2009 20:34",
		"newMorphicProject" : "RAA 10/6/2000 15:46",
		"newMorphicProjectOn:" : "RAA 10/6/2000 15:45",
		"newProjectViewInAWindowFor:" : "ar 8/31/2004 20:53",
		"on:" : "jm 5/14/1998 16:19",
		"services" : "sd 2/1/2002 22:01",
		"unload" : "GabrielOmarCotelli 6/4/2009 20:34" },
	"instance" : {
		"acceptDroppingMorph:event:" : "stephane.ducasse 11/8/2008 15:13",
		"addProjectNameMorph" : "RAA 11/2/2000 09:56",
		"addProjectNameMorphFiller" : "RAA 11/2/2000 10:12",
		"borderWidthForRounding" : "RAA 2/12/2001 14:47",
		"colorAroundName" : "RAA 8/30/2000 19:10",
		"drawOn:" : "jmv 9/7/2009 00:35",
		"editTheName:" : "RAA 11/2/2000 10:41",
		"ensureImageReady" : "raa 2/8/2001 10:40",
		"enter" : "md 10/22/2003 15:51",
		"enterWhenNotPresent" : "RAA 5/17/2000 11:38",
		"extent:" : "RAA 10/27/2000 11:08",
		"fontForName" : "RAA 8/30/2000 19:11",
		"handlesMouseDown:" : "jm 5/4/1998 22:13",
		"handlesMouseOver:" : "sw 9/22/1999 11:41",
		"handlesMouseOverDragging:" : "RAA 1/26/2001 09:03",
		"initialize" : "RAA 1/26/2001 09:14",
		"isEditingName" : "RAA 11/1/2000 22:45",
		"isTheRealProjectPresent" : "RAA 11/2/2000 10:38",
		"lastProjectThumbnail:" : "RAA 7/12/2000 07:44",
		"mouseDown:" : "stephane.ducasse 10/26/2008 17:19",
		"mouseEnter:" : "RAA 7/16/2000 14:14",
		"mouseLeave:" : "RAA 7/16/2000 14:13",
		"mouseLeaveDragging:" : "RAA 1/26/2001 09:03",
		"objectForDataStream:" : "RAA 10/27/2000 11:08",
		"on:" : "RAA 11/2/2000 10:06",
		"project" : "tk 8/30/1999 11:48",
		"project:" : "RAA 11/2/2000 10:06",
		"releaseCachedState" : "RAA 10/27/2000 10:55",
		"safeProjectName" : "gm 2/22/2003 13:14",
		"safeProjectName:" : "gm 2/16/2003 20:34",
		"showBorderAs:" : "RAA 1/26/2001 09:14",
		"showMouseState:" : "kfr 10/9/2004 10:36",
		"storeSegment" : "tk 9/8/1999 17:51",
		"thumbnail" : "di 6/6/2001 21:34",
		"updateImageFrom:" : "RAA 10/27/2000 10:50",
		"updateNamePosition" : "RAA 11/2/2000 10:11",
		"veryDeepFixupWith:" : "tk 1/8/1999 08:56",
		"veryDeepInner:" : "fc 12/23/2004 16:24",
		"wantsDroppedMorph:event:" : "alain.plantec 6/1/2008 19:58",
		"wantsKeyboardFocusFor:" : "RAA 10/20/2000 10:12",
		"wantsRoundedCorners" : "gm 2/16/2003 20:34" } }
